Metadata-Version: 2.1
Name: servussymtowords
Version: 0.2
Summary: Python3 module to convert temperature units and Km to words.
Home-page: https://github.com/carlosplanchon/servussymtowords
Author: Carlos A. Planchón
Author-email: bubbledoloresuruguay2@gmail.com
License: GPL3
Download-URL: https://github.com/carlosplanchon/servussymtowords/archive/v0.2.tar.gz
Keywords: convert,units,words
Platform: UNKNOWN
Classifier: Intended Audience :: Developers
Classifier: Topic :: Software Development :: Build Tools
Classifier: License :: OSI Approved :: GNU General Public License v3 (GPLv3)
Classifier: Programming Language :: Python :: 3
Classifier: Programming Language :: Python :: 3.4
Classifier: Programming Language :: Python :: 3.5
Classifier: Programming Language :: Python :: 3.6
Classifier: Programming Language :: Python :: 3.7
